[1,["ecpdLyjvZBwrvm+cedCcQy","06vvo93QRLTYKy0CPbf7oR","b5QuDp2bVFcrAUXo97cRKK","45jG2vf/hOi7KEf+6Uc4yo","b96IX4P6JAE6VfUeD0FoLd","26Wq8AcyJDq7s7RVMavK9h","f3lIFEgTBHwLLdsB3zw6cT","73c7KC1UhD2ps4UF1UuJ5D"],["node","_textureSetter","_spriteFrame","root","data"],[["cc.Node",["_name","_components","_prefab","_parent","_contentSize","_children","_trs"],2,9,4,1,5,2,7],"cc.SpriteFrame",["cc.Prefab",["_name"],2],["cc.Animation",["node","_clips"],3,1,3],["cc.PrefabInfo",["fileId","root"],2,1],["cc.Sprite",["_dstBlendFactor","node","_materials","_spriteFrame"],2,1,3,6],["cc.ParticleSystem",["_dstBlendFactor","_custom","_stopped","totalParticles","emissionRate","life","lifeVar","angle","angleVar","startSize","startSizeVar","endSize","endSizeVar","startSpinVar","endSpin","endSpinVar","_positionType","speed","speedVar","tangentialAccel","node","_materials","_startColor","_startColorVar","_endColor","_endColorVar","posVar","_spriteFrame"],-17,1,3,8,8,8,8,5,6],["cc.AnimationClip",["_name","_duration","sample","wrapMode","curveData"],-1,11]],[[4,0,1,2],[5,0,1,2,3,2],[2,0,2],[0,0,5,1,2,2],[0,0,3,1,2,4,6,2],[0,0,3,1,2,4,2],[0,0,3,1,2,2],[3,0,1,1],[6,0,1,2,3,4,5,6,7,8,9,10,11,12,13,14,15,16,17,18,19,20,21,22,23,24,25,26,27,21],[7,0,1,2,3,4,5]],[[[{"name":"star_002","rect":[0,0,128,128],"offset":[0,0],"originalSize":[128,128],"capInsets":[0,0,0,0]}],[1],0,[0],[1],[1]],[[{"name":"jiesuan_001","rect":[0,0,128,128],"offset":[0,0],"originalSize":[128,128],"capInsets":[0,0,0,0]}],[1],0,[0],[1],[2]],[[[2,"56_jiesuan_loop_blue"],[3,"56_jiesuan_loop_blue",[-3,-4,-5],[[7,-2,[6]]],[0,"a1qrvHMyFItKn//N74xYpt",-1]],[4,"flare",1,[[1,1,-6,[0],1]],[0,"609G8X6uxJp5/ezKZ2wyFn",1],[5,128,128],[0,0,0,0,0,0,1,0.8,0.8,1]],[5,"ring_001",1,[[1,1,-7,[2],3]],[0,"cbZ8/xxHBNoZjahPM0tOMJ",1],[5,128,128]],[6,"star_002",1,[[8,1,true,false,50,25,1.2,0.3,0,360,30,30,25,30,360,10,60,1,70,20,0,-8,[4],[4,4294967295],[4,4278190080],[4,16777215],[4,0],[0,10,10],5]],[0,"61sR566RxCR7FbsqCzXmnQ",1]]],0,[0,3,1,0,0,1,0,-1,2,0,-2,3,0,-3,4,0,0,2,0,0,3,0,0,4,0,4,1,8],[0,0,0,0,0,0,0],[-1,2,-1,2,-1,2,-1],[0,3,0,4,0,5,6]],[[{"name":"ring_001","rect":[0,0,128,128],"offset":[0,0],"originalSize":[128,128],"capInsets":[0,0,0,0]}],[1],0,[0],[1],[7]],[[[9,"56_jiesuan_loop_blue",1,30,"2",[{},"paths",11,[{"flare":{"props":{"angle":[{"frame":0,"value":0},{"frame":1,"value":-60}]}}},"ring_001",11,[{},"props",11,[{"opacity":[{"frame":0,"value":255},{"frame":1,"value":0}]},"scale",12,[[[{"frame":0},"value",8,[0,0.3,0.3]],[{"frame":1},"value",8,[0,0.9,0.9]]],11,11]]]]]]],0,0,[],[],[]]]]