[1,["3afCpHlzJNiaxMBS6j5joe"],0,[["sp.SkeletonData",["_name","_atlasText","textureNames","_skeletonJson","textures"],-1,3]],[[0,0,1,2,3,4,5]],[[0,"zhendangyun","\nzhendangyun.png\nsize: 1024,256\nformat: RGBA8888\nfilter: Linear,Linear\nrepeat: none\nnormal/yun01\n  rotate: false\n  xy: 2, 2\n  size: 236, 161\n  orig: 236, 161\n  offset: 0, 0\n  index: -1\nnormal/yun02\n  rotate: false\n  xy: 669, 43\n  size: 201, 120\n  orig: 201, 120\n  offset: 0, 0\n  index: -1\nnormal/yun03\n  rotate: false\n  xy: 463, 32\n  size: 204, 131\n  orig: 204, 131\n  offset: 0, 0\n  index: -1\nnormal/yun04\n  rotate: false\n  xy: 240, 30\n  size: 221, 133\n  orig: 221, 133\n  offset: 0, 0\n  index: -1\n",["zhendangyun.png"],{"skeleton":{"hash":"vijfcVNtqvItASIq0uwckYgSh88","spine":"3.6.52","width":371,"height":276,"images":""},"bones":[{"name":"root","x":9.23,"y":125.87},{"name":"bone","parent":"root","x":-52.07,"y":-23.49},{"name":"bone2","parent":"root","x":60.43,"y":-63.97},{"name":"bone3","parent":"root","x":46.71,"y":33.44},{"name":"bone4","parent":"root","x":-38.35,"y":82.15}],"slots":[{"name":"yun04","bone":"bone2","attachment":"yun04"},{"name":"yun03","bone":"bone4","attachment":"yun03"},{"name":"yun02","bone":"bone3","attachment":"yun02"},{"name":"yun01","bone":"bone","attachment":"yun01"}],"skins":{"default":{},"normal":{"yun01":{"yun01":{"name":"normal/yun01","type":"mesh","hull":4,"width":236,"height":161,"uvs":[1,1,0,1,0,0,1,0,0.54078,0.49131],"triangles":[4,2,3,1,2,4,4,3,0,1,4,0],"vertices":[107.9,-78.38,-128.1,-78.38,-128.1,82.62,107.9,82.62,-0.47,3.52],"edges":[0,2,2,4,4,6,0,6]}},"yun02":{"yun02":{"name":"normal/yun02","type":"mesh","hull":4,"width":201,"height":120,"uvs":[1,1,0,1,0,0,1,0,0.41506,0.43213],"triangles":[4,2,3,1,2,4,4,3,0,1,4,0],"vertices":[132.12,-63.31,-68.88,-63.31,-68.88,56.69,132.12,56.69,14.55,4.83],"edges":[0,2,2,4,4,6,0,6]}},"yun03":{"yun03":{"name":"normal/yun03","type":"mesh","hull":4,"width":204,"height":131,"uvs":[1,1,0,1,0,0,1,0,0.51107,0.51669],"triangles":[4,2,3,1,2,4,4,3,0,1,4,0],"vertices":[109.18,-63.02,-94.82,-63.02,-94.82,67.98,109.18,67.98,9.44,0.29],"edges":[0,2,2,4,4,6,0,6]}},"yun04":{"yun04":{"name":"normal/yun04","type":"mesh","hull":4,"width":221,"height":133,"uvs":[1,1,0,1,0,0,1,0,0.37841,0.4898],"triangles":[4,2,3,1,2,4,4,3,0,1,4,0],"vertices":[130.4,-61.9,-90.6,-61.9,-90.6,71.1,130.4,71.1,-6.97,5.96],"edges":[0,2,2,4,4,6,0,6]}}}},"animations":{"chuchang":{"slots":{"yun01":{"color":[{"time":0,"color":"ffffff00"},{"time":0.2667,"color":"ffffffc4"},{"time":0.6,"color":"ffffffff"}]},"yun02":{"color":[{"time":0,"color":"ffffff00"},{"time":0.3,"color":"ffffff8f"},{"time":0.6,"color":"ffffffff"}]},"yun03":{"color":[{"time":0,"color":"ffffff00"},{"time":0.3667,"color":"ffffffe5"},{"time":0.6,"color":"ffffffff"}]},"yun04":{"color":[{"time":0,"color":"ffffff00"},{"time":0.3333,"color":"ffffffd1"},{"time":0.6,"color":"ffffffff"}]}},"bones":{"bone":{"rotate":[{"time":0,"angle":0,"curve":"stepped"},{"time":0.6,"angle":0}],"translate":[{"time":0,"x":-264.94,"y":0},{"time":0.2,"x":-144.54,"y":-11.01},{"time":0.3667,"x":-84.61,"y":-5.5},{"time":0.6,"x":0,"y":0}],"scale":[{"time":0,"x":1,"y":0.895},{"time":0.1333,"x":1,"y":0.627},{"time":0.5333,"x":1,"y":1.039},{"time":0.6,"x":1,"y":1}]},"bone2":{"rotate":[{"time":0,"angle":0,"curve":"stepped"},{"time":0.6,"angle":0}],"translate":[{"time":0,"x":283.12,"y":0},{"time":0.2,"x":136.08,"y":-11.01},{"time":0.4333,"x":19.06,"y":-5.5},{"time":0.6,"x":0,"y":0}],"scale":[{"time":0,"x":1,"y":1},{"time":0.2,"x":1.256,"y":0.816},{"time":0.5333,"x":0.873,"y":0.992},{"time":0.6,"x":1,"y":1}]},"bone3":{"rotate":[{"time":0,"angle":0,"curve":"stepped"},{"time":0.6,"angle":0}],"translate":[{"time":0,"x":283.12,"y":0},{"time":0.2,"x":195.87,"y":-11.01},{"time":0.4333,"x":69.13,"y":-5.5},{"time":0.6,"x":0,"y":0}],"scale":[{"time":0,"x":1,"y":1},{"time":0.2333,"x":1.054,"y":0.728},{"time":0.5,"x":0.919,"y":1.077},{"time":0.6,"x":1,"y":1}]},"bone4":{"rotate":[{"time":0,"angle":0,"curve":"stepped"},{"time":0.6,"angle":0}],"translate":[{"time":0,"x":-189.45,"y":0},{"time":0.2,"x":-110.73,"y":-7.71},{"time":0.4333,"x":-28.29,"y":-5.5},{"time":0.6,"x":0,"y":0}],"scale":[{"time":0,"x":1,"y":1},{"time":0.2,"x":1,"y":0.584},{"time":0.5333,"x":0.854,"y":0.953},{"time":0.6,"x":1,"y":1}]}}},"idle":{"slots":{"yun01":{"color":[{"time":0,"color":"ffffffff","curve":"stepped"},{"time":0.2333,"color":"ffffffff","curve":"stepped"},{"time":0.6667,"color":"ffffffff"}]},"yun02":{"color":[{"time":0,"color":"ffffffff","curve":"stepped"},{"time":0.6667,"color":"ffffffff"}]},"yun03":{"color":[{"time":0,"color":"ffffffff","curve":"stepped"},{"time":0.1333,"color":"ffffffff","curve":"stepped"},{"time":0.6667,"color":"ffffffff"}]},"yun04":{"color":[{"time":0,"color":"ffffffff","curve":"stepped"},{"time":0.1,"color":"ffffffff","curve":"stepped"},{"time":0.6667,"color":"ffffffff"}]}},"bones":{"bone":{"rotate":[{"time":0,"angle":0,"curve":"stepped"},{"time":0.2333,"angle":0,"curve":"stepped"},{"time":0.6667,"angle":0}],"translate":[{"time":0,"x":0,"y":6.92,"curve":[0.25,0,0.75,1]},{"time":0.2333,"x":0,"y":0,"curve":[0.25,0,0.75,1]},{"time":0.5667,"x":0,"y":9.88,"curve":[0.25,0,0.75,1]},{"time":0.6667,"x":0,"y":6.92}],"scale":[{"time":0,"x":1.013,"y":1.02,"curve":[0.25,0,0.75,1]},{"time":0.2333,"x":1,"y":1,"curve":[0.25,0,0.75,1]},{"time":0.5667,"x":1.018,"y":1.029,"curve":[0.25,0,0.75,1]},{"time":0.6667,"x":1.013,"y":1.02}]},"bone2":{"rotate":[{"time":0,"angle":0,"curve":"stepped"},{"time":0.1,"angle":0,"curve":"stepped"},{"time":0.6667,"angle":0}],"translate":[{"time":0,"x":0,"y":2.96,"curve":[0.25,0,0.75,1]},{"time":0.1,"x":0,"y":0,"curve":[0.25,0,0.75,1]},{"time":0.4333,"x":0,"y":9.88,"curve":[0.25,0,0.75,1]},{"time":0.6667,"x":0,"y":2.96}],"scale":[{"time":0,"x":1.005,"y":1.009,"curve":[0.25,0,0.75,1]},{"time":0.1,"x":1,"y":1,"curve":[0.25,0,0.75,1]},{"time":0.4333,"x":1.018,"y":1.029,"curve":[0.25,0,0.75,1]},{"time":0.6667,"x":1.005,"y":1.009}]},"bone3":{"rotate":[{"time":0,"angle":0,"curve":"stepped"},{"time":0.6667,"angle":0}],"translate":[{"time":0,"x":0,"y":0,"curve":[0.25,0,0.75,1]},{"time":0.3333,"x":0,"y":9.88,"curve":[0.25,0,0.75,1]},{"time":0.6667,"x":0,"y":0}],"scale":[{"time":0,"x":1,"y":1,"curve":[0.25,0,0.75,1]},{"time":0.3333,"x":1.018,"y":1.029,"curve":[0.25,0,0.75,1]},{"time":0.6667,"x":1,"y":1}]},"bone4":{"rotate":[{"time":0,"angle":0,"curve":"stepped"},{"time":0.1333,"angle":0,"curve":"stepped"},{"time":0.6667,"angle":0}],"translate":[{"time":0,"x":0,"y":3.95,"curve":[0.25,0,0.75,1]},{"time":0.1333,"x":0,"y":0,"curve":[0.25,0,0.75,1]},{"time":0.4667,"x":0,"y":9.88,"curve":[0.25,0,0.75,1]},{"time":0.6667,"x":0,"y":3.95}],"scale":[{"time":0,"x":1.007,"y":1.012,"curve":[0.25,0,0.75,1]},{"time":0.1333,"x":1,"y":1,"curve":[0.25,0,0.75,1]},{"time":0.4667,"x":1.018,"y":1.029,"curve":[0.25,0,0.75,1]},{"time":0.6667,"x":1.007,"y":1.012}]}},"deform":{"normal":{"yun01":{"yun01":[{"time":0,"curve":[0.25,0,0.75,1]},{"time":0.3333,"offset":1,"vertices":[4.27492,0,8.54989,2.85738,9.97484,-4.28616,15.67484,0,9.97478],"curve":[0.25,0,0.75,1]},{"time":0.6667}]},"yun02":{"yun02":[{"time":0,"curve":[0.25,0,0.75,1]},{"time":0.3333,"vertices":[-14.31946,2.40981,7.57248,1.28749,6.77202,8.61461,-16.44603,3.82872,1.93489,8.61462],"curve":[0.25,0,0.75,1]},{"time":0.6667}]},"yun03":{"yun03":[{"time":0,"curve":[0.25,0,0.75,1]},{"time":0.3,"vertices":[-4.83609,17.04314,1.36661,5.95996,0.00002,6.27371,-12.51022,11.39725,-2.523,8.78336],"curve":[0.25,0,0.75,1]},{"time":0.6667}]},"yun04":{"yun04":[{"time":0,"curve":[0.25,0,0.75,1]},{"time":0.2667,"vertices":[-2.62013,10.43743,-1.31007,-10.81888,2.24964,7.83121,6.92114,8.21267,-6.74868,17.89997],"curve":[0.25,0,0.75,1]},{"time":0.6667}]}}}},"likai":{"slots":{"yun01":{"color":[{"time":0,"color":"ffffffff"},{"time":0.3,"color":"ffffff80"},{"time":0.3667,"color":"ffffff1f"},{"time":0.4333,"color":"ffffff00","curve":"stepped"},{"time":0.5333,"color":"ffffff00"}]},"yun02":{"color":[{"time":0,"color":"ffffffff"},{"time":0.2667,"color":"ffffff8f"},{"time":0.3667,"color":"ffffff1c"},{"time":0.5333,"color":"ffffff00"}]},"yun03":{"color":[{"time":0,"color":"ffffffff"},{"time":0.2,"color":"ffffffe5"},{"time":0.3,"color":"ffffff41"},{"time":0.5333,"color":"ffffff00"}]},"yun04":{"color":[{"time":0,"color":"ffffffff"},{"time":0.2333,"color":"ffffffd1"},{"time":0.3667,"color":"ffffff23"},{"time":0.5333,"color":"ffffff00"}]}},"bones":{"bone":{"rotate":[{"time":0,"angle":0,"curve":"stepped"},{"time":0.5333,"angle":0}],"translate":[{"time":0,"x":0,"y":0},{"time":0.0667,"x":-29.25,"y":-2.75},{"time":0.1667,"x":-84.61,"y":-5.5},{"time":0.3667,"x":-174.21,"y":-11.01},{"time":0.5333,"x":-264.94,"y":0}],"scale":[{"time":0,"x":1,"y":1},{"time":0.0667,"x":0.898,"y":0.978},{"time":0.3667,"x":1.075,"y":0.718},{"time":0.5333,"x":1,"y":0.895}]},"bone2":{"rotate":[{"time":0,"angle":0,"curve":"stepped"},{"time":0.5333,"angle":0}],"translate":[{"time":0,"x":0,"y":0},{"time":0.1333,"x":19.06,"y":-5.5},{"time":0.3667,"x":136.08,"y":-11.01},{"time":0.5333,"x":283.12,"y":0}],"scale":[{"time":0,"x":1,"y":1},{"time":0.0667,"x":1.144,"y":0.898},{"time":0.3667,"x":1.364,"y":0.816},{"time":0.5333,"x":1,"y":1}]},"bone3":{"rotate":[{"time":0,"angle":0,"curve":"stepped"},{"time":0.5333,"angle":0}],"translate":[{"time":0,"x":0,"y":0},{"time":0.1333,"x":69.13,"y":-5.5},{"time":0.3667,"x":195.87,"y":-11.01},{"time":0.5333,"x":283.12,"y":0}],"scale":[{"time":0,"x":1,"y":1},{"time":0.0667,"x":0.815,"y":1.044},{"time":0.3667,"x":1.054,"y":0.728},{"time":0.5333,"x":1,"y":1}]},"bone4":{"rotate":[{"time":0,"angle":0,"curve":"stepped"},{"time":0.5333,"angle":0}],"translate":[{"time":0,"x":0,"y":0},{"time":0.1333,"x":-28.29,"y":-5.5},{"time":0.3,"x":-110.73,"y":-7.71},{"time":0.5333,"x":-189.45,"y":0}],"scale":[{"time":0,"x":1,"y":1},{"time":0.0667,"x":0.676,"y":0.959},{"time":0.3,"x":1,"y":0.584},{"time":0.5333,"x":1,"y":1}]}}}}},[0]]],0,0,[0],[-1],[0]]